auto_OD/All_Models
auto_OD/IoU.py
auto_OD/__init__.py
auto_OD/auto_object_detection.py
auto_OD/auto_object_detection_colab.py
auto_OD/fullyfunctionality.py
auto_OD/inference.py
auto_OD/prepare_data.py
auto_OD/resize_images.py
auto_OD/scenario_detection_pm.py
auto_OD/video_stream.py
auto_OD-0.2.dist-info/METADATA
auto_OD-0.2.dist-info/WHEEL
auto_OD-0.2.dist-info/top_level.txt
auto_OD-0.2.dist-info/RECORD
