Metadata-Version: 2.1
Name: auto-OD
Version: 0.2
Summary: Automatic Object Detection with Tensorflow
Home-page: https://github.com/elina-chertova/auto_OD.git
Author: Elina Chertova
Author-email: elas.2015@mail.ru
License: MIT
Keywords: Tensorflow,Object Detection
Platform: UNKNOWN
Requires-Dist: split-folders
Requires-Dist: scikit-image
Requires-Dist: folium (==0.2.1)
Requires-Dist: imageio
Requires-Dist: ipython (==5.5.0)
Requires-Dist: tf-slim (>=1.1.0)
Requires-Dist: sentencepiece
Requires-Dist: sacrebleu
